{
  "words": [
    {
      "number": 4278,
      "word": "overall",
      "pos": "形容詞、副詞",
      "meaning": "【形】全体の、総合的な 【副】全体的に、概して",
      "nuance": "個別の部分ではなく、すべてをひっくるめた「トータル」の状態を指します。",
      "example_sections": [
        {
          "title": "形容詞の例文",
          "examples": [
            {
              "en": "The overall cost of the project was higher than expected.",
              "ja": "プロジェクトの全体的な費用は予想よりも高かった。",
              "highlight": "overall"
            }
          ]
        },
        {
          "title": "副詞の例文",
          "examples": [
            {
              "en": "Overall, the results were very positive.",
              "ja": "全体的に見て、結果は非常に前向きなものだった。",
              "highlight": "Overall"
            }
          ]
        }
      ],
      "etymology": "over (上に) + all (すべて)",
      "synonyms": [
        {"word": "general", "trans": "全般的な"},
        {"word": "comprehensive", "trans": "包括的な"},
        {"word": "total", "trans": "合計の"}
      ],
      "antonyms": [
        {"word": "partial", "trans": "部分的な"},
        {"word": "specific", "trans": "特定の"}
      ],
      "related": []
    },
    {
      "number": 4284,
      "word": "collapse",
      "pos": "動詞、名詞",
      "meaning": "【自】崩壊する、倒れる 【名】崩壊、破綻",
      "nuance": "建物が重みで崩れるだけでなく、過労で人が倒れたり、経済システムが機能しなくなる際にも使われます。",
      "example_sections": [
        {
          "title": "動詞の例文",
          "examples": [
            {
              "en": "The bridge collapsed during the earthquake.",
              "ja": "その橋は地震の最中に崩壊した。",
              "highlight": "collapsed"
            },
            {
              "en": "He collapsed from exhaustion after the marathon.",
              "ja": "彼はマラソンの後、疲労で倒れた。",
              "highlight": "collapsed"
            }
          ]
        },
        {
          "title": "名詞の例文",
          "examples": [
            {
              "en": "The sudden collapse of the company shocked everyone.",
              "ja": "その企業の突然の倒産（崩壊）は皆を驚かせた。",
              "highlight": "collapse"
            }
          ]
        }
      ],
      "etymology": "col (共に) + labi (滑る)",
      "synonyms": [
        {"word": "break down", "trans": "故障する、崩壊する"},
        {"word": "crumble", "trans": "崩れる"},
        {"word": "fail", "trans": "失敗する、破綻する"}
      ],
      "antonyms": [
        {"word": "build", "trans": "建てる"},
        {"word": "construct", "trans": "建設する"},
        {"word": "recover", "trans": "回復する"}
      ],
      "related": []
    },
    {
      "number": 4285,
      "word": "simultaneous",
      "pos": "形容詞",
      "meaning": "同時の、同時に起こる",
      "nuance": "複数の出来事が、全く同じタイミングで進行していることを強調します。",
      "example_sections": [
        {
          "title": "例文",
          "examples": [
            {
              "en": "There were simultaneous explosions in three different cities.",
              "ja": "3つの異なる都市で、同時に爆発が起こった。",
              "highlight": "simultaneous"
            },
            {
              "en": "The movie will have a simultaneous release in theaters and online.",
              "ja": "その映画は劇場とオンラインで同時公開される予定だ。",
              "highlight": "simultaneous"
            }
          ]
        }
      ],
      "etymology": "ラテン語 simul (同時に)",
      "synonyms": [
        {"word": "coincident", "trans": "一致して起こる"},
        {"word": "concurrent", "trans": "並行した"}
      ],
      "antonyms": [
        {"word": "asynchronous", "trans": "非同期の"},
        {"word": "separate", "trans": "別々の"}
      ],
      "related": [
        {"word": "simultaneously", "trans": "副詞：同時に"},
        {"word": "simultaneous interpretation", "trans": "名詞：同時通訳"}
      ]
    },
    {
      "number": 4286,
      "word": "advocate",
      "pos": "動詞、名詞",
      "meaning": "【他】～を擁護する、主張する 【名】擁護者、支持者",
      "nuance": "公の場で、特定の政策や考え方を強く支持し、推奨することを指します。",
      "example_sections": [
        {
          "title": "動詞の例文",
          "examples": [
            {
              "en": "She advocates for the rights of underprivileged children.",
              "ja": "彼女は恵まれない子供たちの権利を擁護（主張）している。",
              "highlight": "advocates"
            }
          ]
        },
        {
          "title": "名詞の例文",
          "examples": [
            {
              "en": "He is a strong advocate of solar energy.",
              "ja": "彼は太陽エネルギーの強力な支持者だ。",
              "highlight": "advocate"
            }
          ]
        }
      ],
      "etymology": "ad (の方へ) + vocare (呼ぶ) → 助けを呼ぶ、味方する",
      "synonyms": [
        {"word": "support", "trans": "支持する"},
        {"word": "promote", "trans": "促進する"},
        {"word": "proponent", "trans": "支持者"}
      ],
      "antonyms": [
        {"word": "oppose", "trans": "反対する"},
        {"word": "critic", "trans": "批判家"},
        {"word": "adversary", "trans": "敵対者"}
      ],
      "related": [
        {"word": "advocacy", "trans": "名詞：擁護、弁護"}
      ]
    },
    {
      "number": 4289,
      "word": "eccentric",
      "pos": "形容詞、名詞",
      "meaning": "【形】風変わりな、偏屈な 【名】変わり者",
      "nuance": "「中心(center)から外れた(ec-)」が語源。普通の人とは異なる独特で奇妙な行動をとる様子を指します。",
      "example_sections": [
        {
          "title": "形容詞の例文",
          "examples": [
            {
              "en": "My neighbor is an eccentric old man who talks to his plants.",
              "ja": "隣人は植物に話しかけるような風変わりな老人だ。",
              "highlight": "eccentric"
            }
          ]
        }
      ],
      "etymology": "ek (外に) + kentron (中心)",
      "synonyms": [
        {"word": "odd", "trans": "奇妙な"},
        {"word": "peculiar", "trans": "独特な"},
        {"word": "quirky", "trans": "一風変わった"}
      ],
      "antonyms": [
        {"word": "normal", "trans": "普通の"},
        {"word": "conventional", "trans": "型にはまった"},
        {"word": "ordinary", "trans": "平凡な"}
      ],
      "related": [
        {"word": "eccentricity", "trans": "名詞：奇行、偏屈"}
      ]
    },
    {
      "number": 4296,
      "word": "grave",
      "pos": "名詞、形容詞",
      "meaning": "【名】墓 【形】重大な、深刻な",
      "nuance": "形容詞としては、冗談が通じないような「重苦しい」「深刻な」状況を指します。",
      "example_sections": [
        {
          "title": "名詞の例文",
          "examples": [
            {
              "en": "They visited their grandfather's grave every year.",
              "ja": "彼らは毎年、祖父の墓を訪れた。",
              "highlight": "grave"
            }
          ]
        },
        {
          "title": "形容詞の例文",
          "examples": [
            {
              "en": "The patient is in grave danger.",
              "ja": "患者は重大な危険にさらされている。",
              "highlight": "grave"
            },
            {
              "en": "The situation has grave implications for the future.",
              "ja": "その状況は将来に対して深刻な影響を及ぼす。",
              "highlight": "grave"
            }
          ]
        }
      ],
      "etymology": "名詞はゲルマン語源（掘る）。形容詞はラテン語 gravis（重い）。",
      "synonyms": [
        {"word": "tomb", "trans": "墓"},
        {"word": "serious", "trans": "深刻な"},
        {"word": "critical", "trans": "危機的な"}
      ],
      "antonyms": [
        {"word": "trivial", "trans": "些細な"},
        {"word": "slight", "trans": "わずかな"},
        {"word": "cheerful", "trans": "陽気な"}
      ],
      "related": [
        {"word": "gravity", "trans": "名詞：重力、重大さ"},
        {"word": "graveyard", "trans": "名詞：墓地"}
      ]
    },
    {
      "number": 4297,
      "word": "scheme",
      "pos": "名詞、動詞",
      "meaning": "【名】①計画、仕組み ②陰謀 【動】企てる",
      "nuance": "単なる plan よりも組織的、あるいは「企み（裏がある）」というニュアンスで使われることが多いです。",
      "example_sections": [
        {
          "title": "名詞の例文",
          "examples": [
            {
              "en": "The government introduced a new training scheme for the unemployed.",
              "ja": "政府は失業者のための新しい訓練計画（制度）を導入した。",
              "highlight": "scheme"
            },
            {
              "en": "He was involved in a scheme to defraud the company.",
              "ja": "彼は会社をだます陰謀に関与していた。",
              "highlight": "scheme"
            }
          ]
        }
      ],
      "etymology": "ギリシャ語 skhema（形、姿）",
      "synonyms": [
        {"word": "plan", "trans": "計画"},
        {"word": "system", "trans": "体系"},
        {"word": "plot", "trans": "陰謀"}
      ],
      "antonyms": [],
      "related": [
        {"word": "schematic", "trans": "形容詞：図式的な"}
      ]
    },
    {
      "number": 4302,
      "word": "subsequent",
      "pos": "形容詞",
      "meaning": "次の、その後の、続いて起こる",
      "nuance": "ある出来事の「後に続く」時間的順序を指します。",
      "example_sections": [
        {
          "title": "例文",
          "examples": [
            {
              "en": "The first interview was easy, but subsequent ones were much harder.",
              "ja": "最初の面接は簡単だったが、その後の面接はもっと難しかった。",
              "highlight": "subsequent"
            },
            {
              "en": "Subsequent events proved that he was right.",
              "ja": "その後に起こった出来事が、彼の正しさを証明した。",
              "highlight": "Subsequent"
            }
          ]
        }
      ],
      "etymology": "sub (後に) + sequi (続く)",
      "synonyms": [
        {"word": "following", "trans": "次の"},
        {"word": "succeeding", "trans": "継続する"},
        {"word": "consequent", "trans": "結果として生じる"}
      ],
      "antonyms": [
        {"word": "previous", "trans": "前の"},
        {"word": "prior", "trans": "以前の"},
        {"word": "preceding", "trans": "先行する"}
      ],
      "related": [
        {"word": "subsequently", "trans": "副詞：その後"}
      ]
    },
    {
      "number": 4303,
      "word": "procedure",
      "pos": "名詞",
      "meaning": "手続き、手順、処置",
      "nuance": "何かを達成するために、決まった順序で行うべき正式な一連の流れを指します。",
      "example_sections": [
        {
          "title": "例文",
          "examples": [
            {
              "en": "You must follow the proper safety procedures.",
              "ja": "適切な安全手順に従わなければならない。",
              "highlight": "procedures"
            },
            {
              "en": "The surgical procedure took over five hours.",
              "ja": "その手術の処置には5時間以上かかった。",
              "highlight": "procedure"
            }
          ]
        }
      ],
      "etymology": "pro (前へ) + cedere (行く)",
      "synonyms": [
        {"word": "process", "trans": "過程"},
        {"word": "method", "trans": "方法"},
        {"word": "step", "trans": "段階"}
      ],
      "antonyms": [],
      "related": [
        {"word": "proceed", "trans": "動詞：進む、続行する"}
      ]
    },
    {
      "number": 4306,
      "word": "incline",
      "pos": "動詞、名詞",
      "meaning": "【自】（心が）傾く、～したい気になる 【他】～を傾ける 【名】斜面",
      "nuance": "物理的な傾斜だけでなく、「～する傾向がある(be inclined to)」という心理的な傾向にもよく使われます。",
      "example_sections": [
        {
          "title": "動詞の例文",
          "examples": [
            {
              "en": "I'm inclined to agree with your proposal.",
              "ja": "私はあなたの提案に賛成したい気分だ（賛成する傾向がある）。",
              "highlight": "inclined"
            },
            {
              "en": "The road inclines steeply to the left.",
              "ja": "道は左側に急激に傾いている。",
              "highlight": "inclines"
            }
          ]
        }
      ],
      "etymology": "in (中に) + clinare (曲げる、傾ける)",
      "synonyms": [
        {"word": "tend", "trans": "傾向がある"},
        {"word": "lean", "trans": "傾く"},
        {"word": "slope", "trans": "傾斜する"}
      ],
      "antonyms": [
        {"word": "disincline", "trans": "〜する気をなくさせる"}
      ],
      "related": [
        {"word": "inclination", "trans": "名詞：傾向、好み、斜面"}
      ]
    },
    {
      "number": 4308,
      "word": "debt",
      "pos": "名詞",
      "meaning": "借金、恩義",
      "nuance": "お金の借りだけでなく、誰かに助けてもらった「恩（心の借り）」に対しても使われます。",
      "example_sections": [
        {
          "title": "例文",
          "examples": [
            {
              "en": "He worked hard to pay off his debts.",
              "ja": "彼は借金を完済するために懸命に働いた。",
              "highlight": "debts"
            },
            {
              "en": "I owe you a debt of gratitude for your help.",
              "ja": "あなたのご助言に対し、恩義（感謝の借り）を感じています。",
              "highlight": "debt"
            }
          ]
        }
      ],
      "etymology": "dehibere (借りている)",
      "synonyms": [
        {"word": "liability", "trans": "負債"},
        {"word": "obligation", "trans": "義務、恩義"}
      ],
      "antonyms": [
        {"word": "asset", "trans": "資産"},
        {"word": "credit", "trans": "債権"}
      ],
      "related": [
        {"word": "debtor", "trans": "名詞：債務者"}
      ]
    },
    {
      "number": 4309,
      "word": "chat",
      "pos": "動詞、名詞",
      "meaning": "【自】おしゃべりする 【名】おしゃべり、雑談",
      "nuance": "深刻な議論ではなく、リラックスした雰囲気でとりとめもない話をすることを指します。",
      "example_sections": [
        {
          "title": "動詞の例文",
          "examples": [
            {
              "en": "We sat in the cafe and chatted for hours.",
              "ja": "私たちはカフェに座って何時間もおしゃべりした。",
              "highlight": "chatted"
            }
          ]
        }
      ],
      "etymology": "chatter (ぺちゃくちゃ喋る) の短縮形",
      "synonyms": [
        {"word": "gossip", "trans": "噂話をする"},
        {"word": "talk", "trans": "話す"},
        {"word": "converse", "trans": "会話する"}
      ],
      "antonyms": [
        {"word": "silence", "trans": "沈黙"}
      ],
      "related": [
        {"word": "chatterbox", "trans": "名詞：おしゃべりな人"}
      ]
    },
    {
      "number": 4313,
      "word": "interfere",
      "pos": "動詞",
      "meaning": "【自】（with ～）干渉する、邪魔をする、妨げる",
      "nuance": "他人の事柄に勝手に首を突っ込んだり、望ましくない影響を与えて進行を遅らせたりすることを指します。",
      "example_sections": [
        {
          "title": "例文",
          "examples": [
            {
              "en": "Don't interfere in my private business.",
              "ja": "私のプライベートなことに干渉しないでください。",
              "highlight": "interfere"
            },
            {
              "en": "Emotional problems can interfere with a student's ability to learn.",
              "ja": "感情的な問題は、学生の学習能力を妨げる（邪魔する）ことがある。",
              "highlight": "interfering"
            }
          ]
        }
      ],
      "etymology": "inter (間に) + ferire (打つ) → 間に割って入る",
      "synonyms": [
        {"word": "meddle", "trans": "おせっかいを焼く"},
        {"word": "intrude", "trans": "侵入する、邪魔する"},
        {"word": "hinder", "trans": "妨げる"}
      ],
      "antonyms": [
        {"word": "assist", "trans": "助ける"},
        {"word": "facilitate", "trans": "促進する"}
      ],
      "related": [
        {"word": "interference", "trans": "名詞：干渉、妨害"}
      ]
    },
    {
      "number": 4314,
      "word": "fatigue",
      "pos": "名詞、動詞",
      "meaning": "【名】（ひどい）疲労 【動】疲れさせる",
      "nuance": "tiredness よりもフォーマルで、肉体的・精神的な極度の消耗を指します。",
      "example_sections": [
        {
          "title": "名詞の例文",
          "examples": [
            {
              "en": "Driver fatigue is a major cause of road accidents.",
              "ja": "運転手の疲労は、交通事故の主な原因だ。",
              "highlight": "fatigue"
            }
          ]
        }
      ],
      "etymology": "ラテン語 fatigare (疲れさせる)",
      "synonyms": [
        {"word": "exhaustion", "trans": "極度の疲労"},
        {"word": "weariness", "trans": "疲れ、倦怠"}
      ],
      "antonyms": [
        {"word": "energy", "trans": "活力"},
        {"word": "vigor", "trans": "精気"},
        {"word": "refreshment", "trans": "元気回復"}
      ],
      "related": []
    },
    {
      "number": 4316,
      "word": "counterpart",
      "pos": "名詞",
      "meaning": "（異なる組織・場所で）相当するもの、対応する人",
      "nuance": "地位や機能が同じで、別の場所に属しているペアの一方を指します。例：日本の首相とイギリスの首相。",
      "example_sections": [
        {
          "title": "例文",
          "examples": [
            {
              "en": "The foreign minister met with his German counterpart in Berlin.",
              "ja": "外相はベルリンでドイツの（自身に相当する）外相と会談した。",
              "highlight": "counterpart"
            },
            {
              "en": "Our software is much faster than its American counterpart.",
              "ja": "我々のソフトウェアは、アメリカの同種のもの（対応品）よりもはるかに速い。",
              "highlight": "counterpart"
            }
          ]
        }
      ],
      "etymology": "counter (反対の、対応する) + part (部分)",
      "synonyms": [
        {"word": "equivalent", "trans": "同等のもの"},
        {"word": "peer", "trans": "同等の人"},
        {"word": "match", "trans": "釣り合うもの"}
      ],
      "antonyms": [],
      "related": []
    },
    {
      "number": 4318,
      "word": "prominent",
      "pos": "形容詞",
      "meaning": "著名な、目立つ、卓越した",
      "nuance": "社会的に地位が高く有名なことや、物理的に突き出ていて目立つことを指します。",
      "example_sections": [
        {
          "title": "例文",
          "examples": [
            {
              "en": "He is a prominent member of the local community.",
              "ja": "彼は地域社会の著名なメンバーだ。",
              "highlight": "prominent"
            },
            {
              "en": "The church tower is a prominent feature of the landscape.",
              "ja": "教会の塔は、その風景の中で目立つ特徴となっている。",
              "highlight": "prominent"
            }
          ]
        }
      ],
      "etymology": "pro (前に) + minere (突き出る)",
      "synonyms": [
        {"word": "famous", "trans": "有名な"},
        {"word": "distinguished", "trans": "優れた"},
        {"word": "noticeable", "trans": "目立つ"}
      ],
      "antonyms": [
        {"word": "obscure", "trans": "無名の、不明瞭な"},
        {"word": "unknown", "trans": "知られていない"},
        {"word": "inconspicuous", "trans": "目立たない"}
      ],
      "related": [
        {"word": "prominence", "trans": "名詞：卓越、目立つこと"}
      ]
    },
    {
      "number": 4322,
      "word": "extract",
      "pos": "動詞、名詞",
      "meaning": "【動】①（力ずくで）引き出す、抜く ②抽出する 【名】抜粋、エキス",
      "nuance": "中にあるものを「引っ張り出す」イメージ。歯を抜く、情報を聞き出す、エッセンスを取り出す際などに使います。",
      "example_sections": [
        {
          "title": "動詞の例文",
          "examples": [
            {
              "en": "The dentist had to extract two of my teeth.",
              "ja": "歯医者は私の歯を2本抜かなければならなかった。",
              "highlight": "extract"
            },
            {
              "en": "They managed to extract a confession from the suspect.",
              "ja": "彼らは容疑者から自白を引き出すことに成功した。",
              "highlight": "extract"
            }
          ]
        },
        {
          "title": "名詞の例文",
          "examples": [
            {
              "en": "She read a short extract from her new novel.",
              "ja": "彼女は新しい小説の短い抜粋を読み上げた。",
              "highlight": "extract"
            }
          ]
        }
      ],
      "etymology": "ex (外に) + trahere (引く)",
      "synonyms": [
        {"word": "pull out", "trans": "引き抜く"},
        {"word": "derive", "trans": "引き出す"},
        {"word": "excerpt", "trans": "抜粋"}
      ],
      "antonyms": [
        {"word": "insert", "trans": "挿入する"}
      ],
      "related": [
        {"word": "extraction", "trans": "名詞：抽出、摘出"}
      ]
    },
    {
      "number": 4324,
      "word": "condemn",
      "pos": "動詞",
      "meaning": "【他】①強く非難する ②（受身で）刑を宣告する",
      "nuance": "道徳的、あるいは法的な観点から「それは絶対に許されない」と公に否定することを指します。",
      "example_sections": [
        {
          "title": "「非難する」の例文",
          "examples": [
            {
              "en": "The international community condemned the terrorist attack.",
              "ja": "国際社会はそのテロ攻撃を強く非難した。",
              "highlight": "condemned"
            }
          ]
        },
        {
          "title": "「刑を宣告する」の例文",
          "examples": [
            {
              "en": "He was condemned to death for his crimes.",
              "ja": "彼は罪により死刑を宣告された。",
              "highlight": "condemned"
            }
          ]
        }
      ],
      "etymology": "com (強調) + damnare (損害を与える、罰する)",
      "synonyms": [
        {"word": "criticize", "trans": "批判する"},
        {"word": "denounce", "trans": "公然と非難する"},
        {"word": "sentence", "trans": "宣告する"}
      ],
      "antonyms": [
        {"word": "praise", "trans": "賞賛する"},
        {"word": "approve", "trans": "承認する"},
        {"word": "pardon", "trans": "許す"}
      ],
      "related": [
        {"word": "condemnation", "trans": "名詞：非難、宣告"}
      ]
    },
    {
      "number": 4325,
      "word": "aesthetic",
      "pos": "形容詞、名詞",
      "meaning": "【形】美的な、審美的な 【名】美学、美的感覚",
      "nuance": "機能性ではなく、美しさやスタイルに関する感覚を指します。",
      "example_sections": [
        {
          "title": "形容詞の例文",
          "examples": [
            {
              "en": "The building was designed for aesthetic reasons rather than practical ones.",
              "ja": "その建物は実用的な理由ではなく、美的な理由で設計された。",
              "highlight": "aesthetic"
            }
          ]
        }
      ],
      "etymology": "ギリシャ語 aisthesis (感覚)",
      "synonyms": [
        {"word": "artistic", "trans": "芸術的な"},
        {"word": "beautiful", "trans": "美しい"},
        {"word": "exquisite", "trans": "絶妙な"}
      ],
      "antonyms": [
        {"word": "unattractive", "trans": "魅力のない"},
        {"word": "utilitarian", "trans": "実利的な"}
      ],
      "related": [
        {"word": "aesthetics", "trans": "名詞：美学"}
      ]
    },
    {
      "number": 4329,
      "word": "peer",
      "pos": "動詞、名詞",
      "meaning": "【自】じっと見る、凝視する 【名】同等の人、仲間",
      "nuance": "動詞としては、暗闇や霧の中で何かを見ようとして「目を細めてじっと見る」様子を指します。",
      "example_sections": [
        {
          "title": "動詞の例文",
          "examples": [
            {
              "en": "She peered through the mist, trying to find the house.",
              "ja": "彼女は家を見つけようと、霧の中をじっと見つめた。",
              "highlight": "peered"
            }
          ]
        },
        {
          "title": "名詞の例文",
          "examples": [
            {
              "en": "Teenagers often feel pressure to behave like their peers.",
              "ja": "10代の若者は、しばしば仲間（同等の友人）と同じように振る舞うようプレッシャーを感じる。",
              "highlight": "peers"
            }
          ]
        }
      ],
      "etymology": "名詞はラテン語 par (等しい)。動詞は「現れる」から転じた。",
      "synonyms": [
        {"word": "gaze", "trans": "凝視する"},
        {"word": "stare", "trans": "見つめる"},
        {"word": "equal", "trans": "同等の人"}
      ],
      "antonyms": [
        {"word": "glance", "trans": "ちらりと見る"},
        {"word": "superior", "trans": "目上の人"}
      ],
      "related": [
        {"word": "peer pressure", "trans": "名詞：同調圧力"}
      ]
    },
    {
      "number": 4330,
      "word": "load",
      "pos": "名詞、動詞",
      "meaning": "【名】荷、負担 【動】積む",
      "nuance": "物理的な荷物だけでなく、仕事量や責任といった「重荷」に対しても使われます。",
      "example_sections": [
        {
          "title": "名詞の例文",
          "examples": [
            {
              "en": "The truck was carrying a heavy load of bricks.",
              "ja": "トラックはレンガの重い積荷を運んでいた。",
              "highlight": "load"
            },
            {
              "en": "He has a heavy teaching load this semester.",
              "ja": "彼は今学期、授業の負担（受け持ち数）が重い。",
              "highlight": "load"
            }
          ]
        },
        {
          "title": "動詞の例文",
          "examples": [
            {
              "en": "Wait a minute, the webpage is still loading.",
              "ja": "ちょっと待って、ウェブページがまだ読み込み中（データを積んでいる最中）だ。",
              "highlight": "loading"
            }
          ]
        }
      ],
      "etymology": "ゲルマン語源 (道、運ぶこと)",
      "synonyms": [
        {"word": "cargo", "trans": "積荷"},
        {"word": "burden", "trans": "重荷"},
        {"word": "weight", "trans": "重量"}
      ],
      "antonyms": [
        {"word": "unload", "trans": "荷を下ろす"}
      ],
      "related": []
    },
    {
      "number": 4331,
      "word": "immense",
      "pos": "形容詞",
      "meaning": "ものすごい、巨大な、膨大な",
      "nuance": "「測れないほど(in-)大きい(metiri)」が語源。桁外れの規模や量に対して使われます。",
      "example_sections": [
        {
          "title": "例文",
          "examples": [
            {
              "en": "The project was an immense success.",
              "ja": "そのプロジェクトは、ものすごい成功を収めた。",
              "highlight": "immense"
            },
            {
              "en": "There is an immense amount of work to be done.",
              "ja": "やるべき仕事が膨大にある。",
              "highlight": "immense"
            }
          ]
        }
      ],
      "etymology": "in (否定) + metiri (測る)",
      "synonyms": [
        {"word": "enormous", "trans": "巨大な"},
        {"word": "vast", "trans": "広大な"},
        {"word": "massive", "trans": "どっしりと大きい"}
      ],
      "antonyms": [
        {"word": "tiny", "trans": "とても小さい"},
        {"word": "minute", "trans": "微小な"},
        {"word": "small", "trans": "小さい"}
      ],
      "related": [
        {"word": "immensely", "trans": "副詞：非常に"}
      ]
    },
    {
      "number": 4333,
      "word": "discard",
      "pos": "動詞",
      "meaning": "【他】（不要なものを）捨てる、放棄する",
      "nuance": "「カードを捨てる」が語源。役に立たなくなった、あるいは不要になったものを意識的に取り除くことを指します。",
      "example_sections": [
        {
          "title": "例文",
          "examples": [
            {
              "en": "Discard any broken toys for safety.",
              "ja": "安全のため、壊れたおもちゃはすべて捨てなさい。",
              "highlight": "Discard"
            },
            {
              "en": "The old theory was discarded when new evidence appeared.",
              "ja": "新しい証拠が現れたとき、古い理論は放棄された。",
              "highlight": "discarded"
            }
          ]
        }
      ],
      "etymology": "dis (離れて) + card (トランプのカード)",
      "synonyms": [
        {"word": "throw away", "trans": "投げ捨てる"},
        {"word": "abandon", "trans": "見捨てる"},
        {"word": "dump", "trans": "どさっと捨てる"}
      ],
      "antonyms": [
        {"word": "keep", "trans": "保つ"},
        {"word": "preserve", "trans": "保存する"},
        {"word": "retain", "trans": "保持する"}
      ],
      "related": []
    },
    {
      "number": 4335,
      "word": "emergency",
      "pos": "名詞",
      "meaning": "緊急事態、非常時",
      "nuance": "予期せぬ重大な出来事が「現れる(emerge)」こと。直ちに対応が必要な状態を指します。",
      "example_sections": [
        {
          "title": "例文",
          "examples": [
            {
              "en": "In case of emergency, break the glass.",
              "ja": "緊急時には、ガラスを割ってください。",
              "highlight": "emergency"
            },
            {
              "en": "The pilot declared an emergency and landed safely.",
              "ja": "パイロットは緊急事態を宣言し、無事に着陸した。",
              "highlight": "emergency"
            }
          ]
        }
      ],
      "etymology": "e (外に) + mergere (浸す、潜る) → 現れ出ること",
      "synonyms": [
        {"word": "crisis", "trans": "危機"},
        {"word": "urgency", "trans": "緊急性"}
      ],
      "antonyms": [],
      "related": [
        {"word": "emerge", "trans": "動詞：現れる"}
      ]
    },
    {
      "number": 4336,
      "word": "tap",
      "pos": "名詞、動詞",
      "meaning": "【名】①蛇口、栓 ②（軽く）叩くこと 【動】①軽く叩く ②（資源などを）引き出す",
      "nuance": "動詞の「引き出す」は、木に穴を開けて樹液を採ることから転じて、潜在能力やエネルギーを利用する際にも使われます。",
      "example_sections": [
        {
          "title": "名詞の例文",
          "examples": [
            {
              "en": "Don't leave the tap running.",
              "ja": "蛇口を出しっぱなしにしないで。",
              "highlight": "tap"
            }
          ]
        },
        {
          "title": "動詞の例文",
          "examples": [
            {
              "en": "He tapped me on the shoulder to get my attention.",
              "ja": "彼は私の注意を引くために、肩を軽く叩いた。",
              "highlight": "tapped"
            },
            {
              "en": "We need to tap new sources of energy.",
              "ja": "我々は新しいエネルギー源を引き出す（利用する）必要がある。",
              "highlight": "tap"
            }
          ]
        }
      ],
      "etymology": "ゲルマン語源 (栓、樽から酒を出すこと)",
      "synonyms": [
        {"word": "faucet", "trans": "蛇口（米）"},
        {"word": "pat", "trans": "軽く叩く"},
        {"word": "utilize", "trans": "利用する"}
      ],
      "antonyms": [],
      "related": []
    },
    {
      "number": 4337,
      "word": "sacrifice",
      "pos": "名詞、動詞",
      "meaning": "【名】犠牲（的行為）、いけにえ 【動】～を犠牲にする",
      "nuance": "「聖なる(sacer)ものにする(facere)」が語源。より大切なもののために、価値あるものを進んで手放すことを指します。",
      "example_sections": [
        {
          "title": "名詞の例文",
          "examples": [
            {
              "en": "Parents often make huge sacrifices for their children.",
              "ja": "親はしばしば、子供のために多大な犠牲を払う。",
              "highlight": "sacrifices"
            }
          ]
        },
        {
          "title": "動詞の例文",
          "examples": [
            {
              "en": "She sacrificed her career to look after her sick mother.",
              "ja": "彼女は病気の母を看病するために、自分のキャリアを犠牲にした。",
              "highlight": "sacrificed"
            }
          ]
        }
      ],
      "etymology": "sacer (聖なる) + facere (作る)",
      "synonyms": [
        {"word": "offering", "trans": "捧げ物"},
        {"word": "surrender", "trans": "明け渡す、断念する"},
        {"word": "give up", "trans": "諦める"}
      ],
      "antonyms": [
        {"word": "keep", "trans": "保つ"},
        {"word": "take", "trans": "取る"}
      ],
      "related": [
        {"word": "sacred", "trans": "形容詞：神聖な"}
      ]
    },
    {
      "number": 4340,
      "word": "fierce",
      "pos": "形容詞",
      "meaning": "どう猛な、激しい、猛烈な",
      "nuance": "攻撃性が強く、荒々しい様子を指します。動物だけでなく、競争や天候、感情の激しさにも使われます。",
      "example_sections": [
        {
          "title": "例文",
          "examples": [
            {
              "en": "A fierce dog guarded the entrance.",
              "ja": "どう猛な犬が入り口を守っていた。",
              "highlight": "fierce"
            },
            {
              "en": "The two companies are in fierce competition.",
              "ja": "その2社は猛烈な競争を繰り広げている。",
              "highlight": "fierce"
            }
          ]
        }
      ],
      "etymology": "ラテン語 ferus (野生の)",
      "synonyms": [
        {"word": "ferocious", "trans": "残忍な"},
        {"word": "intense", "trans": "強烈な"},
        {"word": "violent", "trans": "暴力的な、激しい"}
      ],
      "antonyms": [
        {"word": "gentle", "trans": "穏やかな"},
        {"word": "mild", "trans": "緩やかな"},
        {"word": "tame", "trans": "飼い慣らされた"}
      ],
      "related": [
        {"word": "fiercely", "trans": "副詞：猛烈に"}
      ]
    },
    {
      "number": 4341,
      "word": "enhance",
      "pos": "動詞",
      "meaning": "【他】（質・能力・価値などを）高める、向上させる",
      "nuance": "すでに良い状態のものを、さらに良く、魅力的にすることを指します。",
      "example_sections": [
        {
          "title": "例文",
          "examples": [
            {
              "en": "The new lighting will enhance the beauty of the garden.",
              "ja": "新しい照明が庭の美しさをさらに高めるだろう。",
              "highlight": "enhance"
            },
            {
              "en": "They added some spices to enhance the flavor of the soup.",
              "ja": "彼らはスープの風味を高めるためにスパイスを加えた。",
              "highlight": "enhance"
            }
          ]
        }
      ],
      "etymology": "in (中に) + altus (高い) → 高める",
      "synonyms": [
        {"word": "improve", "trans": "改善する"},
        {"word": "boost", "trans": "押し上げる"},
        {"word": "heighten", "trans": "高める"}
      ],
      "antonyms": [
        {"word": "diminish", "trans": "減らす"},
        {"word": "reduce", "trans": "減少させる"},
        {"word": "impair", "trans": "損なう"}
      ],
      "related": [
        {"word": "enhancement", "trans": "名詞：向上、強化"}
      ]
    },
    {
      "number": 4345,
      "word": "thereby",
      "pos": "副詞",
      "meaning": "そのために、それによって、そうすることで",
      "nuance": "先行する行動の結果として「必然的に次のことが起こる」という論理的なつながりを示します。フォーマルな表現です。",
      "example_sections": [
        {
          "title": "例文",
          "examples": [
            {
              "en": "He worked weekends, thereby earning enough money to buy a car.",
              "ja": "彼は週末も働き、それによって車を買うのに十分なお金を稼いだ。",
              "highlight": "thereby"
            }
          ]
        }
      ],
      "etymology": "there (そこ) + by (によって)",
      "synonyms": [
        {"word": "thus", "trans": "このようにして"},
        {"word": "consequently", "trans": "結果として"},
        {"word": "by that means", "trans": "その手段によって"}
      ],
      "antonyms": [],
      "related": []
    },
    {
      "number": 4347,
      "word": "rite",
      "pos": "名詞",
      "meaning": "（宗教的・伝統的な）儀式、しきたり",
      "nuance": "決まった形や手順で行われる厳粛な行事を指します。「成人式(rite of passage)」などが代表的です。",
      "example_sections": [
        {
          "title": "例文",
          "examples": [
            {
              "en": "The tribe performs ancient burial rites.",
              "ja": "その部族は古代の埋葬儀式を執り行う。",
              "highlight": "rites"
            }
          ]
        }
      ],
      "etymology": "ラテン語 ritus (宗教的儀式)",
      "synonyms": [
        {"word": "ceremony", "trans": "式典"},
        {"word": "ritual", "trans": "（日常的な）儀式、慣習"},
        {"word": "custom", "trans": "習わし"}
      ],
      "antonyms": [],
      "related": [
        {"word": "ritual", "trans": "形容詞：儀式的な／名詞：儀式"}
      ]
    },
    {
      "number": 4349,
      "word": "infer",
      "pos": "動詞",
      "meaning": "【他】～を推論する、推測する",
      "nuance": "「中に(in)運ぶ(ferre)」が語源。提示された事実や証拠から、直接言われていない結論を導き出す知的なプロセスを指します。",
      "example_sections": [
        {
          "title": "例文",
          "examples": [
            {
              "en": "What can we infer from the data provided in the chart?",
              "ja": "チャートに示されたデータから、何を推論できるだろうか？",
              "highlight": "infer"
            },
            {
              "en": "I inferred from her silence that she was angry.",
              "ja": "彼女の沈黙から、彼女が怒っているのだと察した（推測した）。",
              "highlight": "inferred"
            }
          ]
        }
      ],
      "etymology": "in (中に) + ferre (運ぶ)",
      "synonyms": [
        {"word": "deduce", "trans": "演繹する"},
        {"word": "conclude", "trans": "結論づける"},
        {"word": "surmise", "trans": "推測する"}
      ],
      "antonyms": [],
      "related": [
        {"word": "inference", "trans": "名詞：推論、推測"}
      ]
    },
    {
      "number": 4350,
      "word": "exaggerate",
      "pos": "動詞",
      "meaning": "【他】～を誇張する、大げさに言う",
      "nuance": "事実を実際よりも大きく、あるいはひどく見せるように話すことを指します。",
      "example_sections": [
        {
          "title": "例文",
          "examples": [
            {
              "en": "Stop exaggerating! The fish wasn't that big.",
              "ja": "誇張するのはやめて！その魚はそんなに大きくなかったよ。",
              "highlight": "exaggerating"
            },
            {
              "en": "The importance of this discovery cannot be exaggerated.",
              "ja": "この発見の重要性は、いくら強調（誇張）してもしすぎることはない。",
              "highlight": "exaggerated"
            }
          ]
        }
      ],
      "etymology": "ex (外に) + agger (積み土) → 山のように積み上げる",
      "synonyms": [
        {"word": "overstate", "trans": "大げさに言う"},
        {"word": "magnify", "trans": "拡大する"},
        {"word": "embellish", "trans": "（話を）盛る"}
      ],
      "antonyms": [
        {"word": "understate", "trans": "控えめに言う"},
        {"word": "minimize", "trans": "最小限に見せる"}
      ],
      "related": [
        {"word": "exaggeration", "trans": "名詞：誇張"}
      ]
    },
    {
      "number": 4355,
      "word": "precede",
      "pos": "動詞",
      "meaning": "【他】（順序・時間的に）～に先立つ、先行する",
      "nuance": "「前へ(pre-)行く(cedere)」が語源。何かが起こる前にすでに存在している、あるいは前に配置されていることを指します。",
      "example_sections": [
        {
          "title": "例文",
          "examples": [
            {
              "en": "The storm was preceded by a long period of calm.",
              "ja": "嵐の前に、長い静けさがあった（静けさが嵐に先立った）。",
              "highlight": "preceded"
            },
            {
              "en": "A short introduction precedes the first chapter.",
              "ja": "第1章の前に、短い導入文がある。",
              "highlight": "precedes"
            }
          ]
        }
      ],
      "etymology": "pre (前に) + cedere (行く)",
      "synonyms": [
        {"word": "come before", "trans": "前に来る"},
        {"word": "lead up to", "trans": "〜に至る、先んじる"},
        {"word": "anticipate", "trans": "先行する、予期する"}
      ],
      "antonyms": [
        {"word": "follow", "trans": "続く"},
        {"word": "succeed", "trans": "継承する、後に続く"}
      ],
      "related": [
        {"word": "precedent", "trans": "名詞：前例"},
        {"word": "preceding", "trans": "形容詞：前の"}
      ]
    },
    {
      "number": 4357,
      "word": "contradiction",
      "pos": "名詞",
      "meaning": "矛盾、反対の主張",
      "nuance": "「反対に(contra)言う(dictio)」が語源。2つの事実や発言が互いに食い違っていて、両立しない状態を指します。",
      "example_sections": [
        {
          "title": "例文",
          "examples": [
            {
              "en": "There is a direct contradiction between his words and his actions.",
              "ja": "彼の言葉と行動の間には、直接的な矛盾がある。",
              "highlight": "contradiction"
            }
          ]
        }
      ],
      "etymology": "contra (反対に) + dicere (言う)",
      "synonyms": [
        {"word": "discrepancy", "trans": "不一致"},
        {"word": "conflict", "trans": "衝突、葛藤"},
        {"word": "inconsistency", "trans": "一貫性のなさ"}
      ],
      "antonyms": [
        {"word": "consistency", "trans": "一貫性"},
        {"word": "agreement", "trans": "一致"},
        {"word": "harmony", "trans": "調和"}
      ],
      "related": [
        {"word": "contradict", "trans": "動詞：～と矛盾する"},
        {"word": "contradictory", "trans": "形容詞：矛盾した"}
      ]
    },
    {
      "number": 4359,
      "word": "faculty",
      "pos": "名詞",
      "meaning": "①（身体・精神の）機能、能力 ②学部 ③（学部の）全教員",
      "nuance": "元々は「何かをする力」を指し、そこから大学で専門能力を教える「組織（学部）」やそのメンバーへと意味が広がりました。",
      "example_sections": [
        {
          "title": "「能力・機能」の例文",
          "examples": [
            {
              "en": "He still has all his mental faculties at the age of 90.",
              "ja": "彼は90歳になっても、精神機能（知的能力）はすべて健全だ。",
              "highlight": "faculties"
            }
          ]
        },
        {
          "title": "「学部・教員」の例文",
          "examples": [
            {
              "en": "He is a professor in the Faculty of Law.",
              "ja": "彼は法学部の教授だ。",
              "highlight": "Faculty"
            },
            {
              "en": "The school has a dedicated faculty.",
              "ja": "その学校には献身的な教員団がいる。",
              "highlight": "faculty"
            }
          ]
        }
      ],
      "etymology": "facere (作る、行う) → 行う能力",
      "synonyms": [
        {"word": "ability", "trans": "能力"},
        {"word": "department", "trans": "部門、学科"},
        {"word": "staff", "trans": "職員、教員"}
      ],
      "antonyms": [
        {"word": "inability", "trans": "無能"}
      ],
      "related": []
    },
    {
      "number": 4361,
      "word": "grab",
      "pos": "動詞、名詞",
      "meaning": "【動】つかむ、ひっつかむ 【名】つかむこと",
      "nuance": "丁寧に持つのではなく、急いで、あるいは乱暴に「ガシッとつかみ取る」動作を指します。",
      "example_sections": [
        {
          "title": "例文",
          "examples": [
            {
              "en": "She grabbed her bag and ran out of the door.",
              "ja": "彼女はバッグをひっつかんでドアから駆け出した。",
              "highlight": "grabbed"
            },
            {
              "en": "Let's grab a quick lunch before the meeting.",
              "ja": "会議の前に、素早くランチを済ませよう（ランチをつかみ取ろう）。",
              "highlight": "grab"
            }
          ]
        }
      ],
      "etymology": "ゲルマン語源 (つかむ、握る)",
      "synonyms": [
        {"word": "seize", "trans": "（法的に・力ずくで）つかむ"},
        {"word": "snatch", "trans": "ひったくる"},
        {"word": "clutch", "trans": "ぎゅっと握る"}
      ],
      "antonyms": [
        {"word": "release", "trans": "放す"},
        {"word": "let go", "trans": "手放す"},
        {"word": "drop", "trans": "落とす"}
      ],
      "related": []
    },
    {
      "number": 4362,
      "word": "embrace",
      "pos": "動詞、名詞",
      "meaning": "【動】①抱擁する ②（思想などを）受け入れる 【名】抱擁",
      "nuance": "「腕(brace)の中(em-)に入れる」が語源。物理的に抱きしめるだけでなく、新しいアイデアや変化を「喜んで受け入れる」という意味でもよく使われます。",
      "example_sections": [
        {
          "title": "「抱擁する」の例文",
          "examples": [
            {
              "en": "They embraced each other at the airport.",
              "ja": "彼らは空港でお互いを抱きしめ合った。",
              "highlight": "embraced"
            }
          ]
        },
        {
          "title": "「受け入れる」の例文",
          "examples": [
            {
              "en": "The company has fully embraced digital technology.",
              "ja": "その企業はデジタル技術を完全に取り入れた（受け入れた）。",
              "highlight": "embraced"
            }
          ]
        }
      ],
      "etymology": "en (中に) + brace (腕)",
      "synonyms": [
        {"word": "hug", "trans": "抱きしめる"},
        {"word": "accept", "trans": "受け入れる"},
        {"word": "adopt", "trans": "採用する"}
      ],
      "antonyms": [
        {"word": "reject", "trans": "拒絶する"},
        {"word": "exclude", "trans": "排除する"},
        {"word": "shun", "trans": "避ける"}
      ],
      "related": []
    },
    {
      "number": 4367,
      "word": "assert",
      "pos": "動詞",
      "meaning": "【他】（自信を持って）主張する、断言する",
      "nuance": "「～の方へ(ad-)結びつける(serere)」が語源。証拠が不十分な場合でも、自分の意見や権利を「これが正しい」とはっきり強く主張することを指します。",
      "example_sections": [
        {
          "title": "例文",
          "examples": [
            {
              "en": "He continued to assert his innocence throughout the trial.",
              "ja": "彼は裁判の間ずっと、自分の無実を主張し続けた。",
              "highlight": "assert"
            },
            {
              "en": "The new director began to assert her authority.",
              "ja": "新しい取締役は、自らの権威を行使し（主張し）始めた。",
              "highlight": "assert"
            }
          ]
        }
      ],
      "etymology": "ad (の方へ) + serere (繋ぐ、並べる)",
      "synonyms": [
        {"word": "claim", "trans": "主張する"},
        {"word": "declare", "trans": "宣言する"},
        {"word": "maintain", "trans": "（意見を）維持する、主張する"}
      ],
      "antonyms": [
        {"word": "deny", "trans": "否定する"},
        {"word": "doubt", "trans": "疑う"},
        {"word": "abandon", "trans": "（権利などを）放棄する"}
      ],
      "related": [
        {"word": "assertion", "trans": "名詞：主張、断言"},
        {"word": "assertive", "trans": "形容詞：断定的な、積極的な"}
      ]
    }
  ]
}
